setup.py
cloudyday/__init__.py
cloudyday/cloudyday.py
cloudyday.egg-info/PKG-INFO
cloudyday.egg-info/SOURCES.txt
cloudyday.egg-info/dependency_links.txt
cloudyday.egg-info/requires.txt
cloudyday.egg-info/top_level.txt