Metadata-Version: 2.1
Name: cloudyday
Version: 1.0.0
Summary: Weather forecast data
Home-page: 
Author: Sowmya
Author-email: sowmyachinni000@gmail.com
License: MIT
Keywords: weather,forecast,openweather
Classifier: Development Status :: 3 - Alpha
Classifier: Intended Audience :: Developers
Classifier: Topic :: Software Development :: Build Tools
Classifier: License :: OSI Approved :: MIT License
Classifier: Programming Language :: Python :: 3.13
Requires-Dist: requests
